{
  "cardType": "trainer",
  "effect": {
    "jp": "このカードをつけている「ポケモンVMAX」の最大HPは「100」小さくなり、そのポケモンが、相手のポケモンからワザのダメージを受けてきぜつしたとき、とられるサイドは1枚少なくなる。（このカードを手札からつけるとき、そのポケモンがきぜつするなら、つけられない。）"
  },
  "imageUrls": {
    "lg": {
      "jp": "https://limitlesstcg.nyc3.cdn.digitaloceanspaces.com/tpc/S3a/S3a_68_R_JP.png"
    },
    "sm": {
      "jp": "https://limitlesstcg.nyc3.cdn.digitaloceanspaces.com/tpc/S3a/S3a_68_R_JP_SM.png"
    },
    "xs": {
      "jp": "https://limitlesstcg.nyc3.cdn.digitaloceanspaces.com/tpc/S3a/S3a_68_R_JP_XS.png"
    }
  },
  "language": "jp",
  "name": {
    "jp": "英雄のメダル"
  },
  "number": "68",
  "rarity": "u",
  "regulation": "d",
  "set": "S3a",
  "type": "tool"
}