{
  "attacks": [
    {
      "cost": [
        "c"
      ],
      "effect": {
        "en": "Attach up to 2 [G] Energy cards from your hand to Weepinbell."
      },
      "name": {
        "en": "Growth"
      }
    },
    {
      "cost": [
        "g",
        "c"
      ],
      "dmg": "30×",
      "effect": {
        "en": "Flip 2 coins. This attack does 30 damage times the number of heads."
      },
      "name": {
        "en": "Double Razor Leaf"
      }
    }
  ],
  "cardType": "pokemon",
  "hp": 70,
  "imageUrls": {
    "lg": {
      "en": "https://images.pokemontcg.io/ecard2/65_hires.png"
    },
    "sm": {
      "en": "https://images.pokemontcg.io/ecard2/65.png"
    },
    "xs": {
      "en": "https://images.pokemontcg.io/ecard2/65.png"
    }
  },
  "language": "en",
  "name": {
    "en": "Weepinbell"
  },
  "number": "65",
  "rarity": "u",
  "resistance": [],
  "retreat": 1,
  "set": "E2",
  "stage": "stage1",
  "type": [
    "grass"
  ],
  "weakness": [
    "fire"
  ]
}