{
  "attacks": [
    {
      "cost": [
        "c"
      ],
      "dmg": "20",
      "effect": {
        "jp": "相手のバトルポケモンが持っているワザを1つ選ぶ。次の相手の番、このワザを受けたポケモンは、選ばれたワザを使えない。"
      },
      "name": {
        "jp": "ドわすれ"
      }
    },
    {
      "cost": [
        "w",
        "c",
        "c"
      ],
      "dmg": "60+",
      "effect": {
        "jp": "コインを1回投げオモテなら、30ダメージを追加。"
      },
      "name": {
        "jp": "つきあげる"
      }
    }
  ],
  "cardType": "pokemon",
  "hp": 100,
  "imageUrls": {
    "lg": {
      "jp": "https://limitlesstcg.nyc3.cdn.digitaloceanspaces.com/tpc/XY5t/XY5t_19_R_JP.png"
    },
    "sm": {
      "jp": "https://limitlesstcg.nyc3.cdn.digitaloceanspaces.com/tpc/XY5t/XY5t_19_R_JP_SM.png"
    },
    "xs": {
      "jp": "https://limitlesstcg.nyc3.cdn.digitaloceanspaces.com/tpc/XY5t/XY5t_19_R_JP_XS.png"
    }
  },
  "languages": [
    "jp"
  ],
  "name": {
    "jp": "ナマズン"
  },
  "number": "19",
  "rarity": "u",
  "resistance": [],
  "retreat": 3,
  "set": "XY5t",
  "stage": "stage1",
  "type": [
    "water"
  ],
  "weakness": [
    "grass"
  ]
}