{
  "attacks": [
    {
      "cost": [
        "d"
      ],
      "dmg": "10",
      "effect": {},
      "name": {
        "jp": "つきさす"
      }
    }
  ],
  "cardType": "pokemon",
  "hp": 70,
  "imageUrls": {
    "lg": {
      "jp": "https://limitlesstcg.nyc3.cdn.digitaloceanspaces.com/tpc/SVI/SVI_35_R_JP.png"
    },
    "sm": {
      "jp": "https://limitlesstcg.nyc3.cdn.digitaloceanspaces.com/tpc/SVI/SVI_35_R_JP_SM.png"
    },
    "xs": {
      "jp": "https://limitlesstcg.nyc3.cdn.digitaloceanspaces.com/tpc/SVI/SVI_35_R_JP_XS.png"
    }
  },
  "language": "jp",
  "name": {
    "jp": "コマタナ"
  },
  "number": "35",
  "regulation": "h",
  "resistance": [],
  "retreat": 1,
  "set": "SVI",
  "stage": "basic",
  "type": [
    "darkness"
  ],
  "weakness": [
    "grass"
  ]
}