{
  "attacks": [
    {
      "cost": [
        "c",
        "c"
      ],
      "dmg": "20",
      "effect": {},
      "name": {
        "jp": "タネばくだん"
      }
    }
  ],
  "cardType": "pokemon",
  "hp": 40,
  "imageUrls": {
    "lg": {
      "jp": "https://limitlesstcg.nyc3.cdn.digitaloceanspaces.com/tpc/S11/S11_3_R_JP.png"
    },
    "sm": {
      "jp": "https://limitlesstcg.nyc3.cdn.digitaloceanspaces.com/tpc/S11/S11_3_R_JP_SM.png"
    },
    "xs": {
      "jp": "https://limitlesstcg.nyc3.cdn.digitaloceanspaces.com/tpc/S11/S11_3_R_JP_XS.png"
    }
  },
  "language": "jp",
  "name": {
    "jp": "ヒマナッツ"
  },
  "number": "3",
  "rarity": "c",
  "regulation": "f",
  "resistance": [],
  "retreat": 1,
  "set": "S11",
  "stage": "basic",
  "type": [
    "grass"
  ],
  "weakness": [
    "fire"
  ]
}