{
  "attacks": [
    {
      "cost": [
        "c"
      ],
      "effect": {
        "en": "Flip a coin. If heads, the Defending Pokémon is now Poisoned."
      },
      "name": {
        "en": "Poison Fang"
      }
    },
    {
      "cost": [
        "g",
        "c",
        "c"
      ],
      "dmg": "40",
      "effect": {},
      "name": {
        "en": "Bite"
      }
    }
  ],
  "cardType": "pokemon",
  "hp": 70,
  "imageUrls": {
    "lg": {
      "en": "https://images.pokemontcg.io/ex13/32_hires.png"
    },
    "sm": {
      "en": "https://images.pokemontcg.io/ex13/32.png"
    },
    "xs": {
      "en": "https://images.pokemontcg.io/ex13/32.png"
    }
  },
  "languages": [
    "en"
  ],
  "name": {
    "en": "Seviper"
  },
  "number": "32",
  "rarity": "r",
  "resistance": [],
  "retreat": 1,
  "set": "HP",
  "stage": "basic",
  "type": [
    "grass"
  ],
  "weakness": [
    "psychic"
  ]
}