{
  "attacks": [
    {
      "cost": "p",
      "dmg": "10+",
      "effect": {
        "en": "Flip a coin. If heads, this attack does 10 damage plus 10 more damage."
      },
      "name": {
        "en": "Knock Away"
      }
    }
  ],
  "cardType": "pokemon",
  "hp": 50,
  "imageUrls": {
    "lg": {
      "en": "https://images.pokemontcg.io/ex9/65_hires.png"
    },
    "sm": {
      "en": "https://images.pokemontcg.io/ex9/65.png"
    },
    "xs": {
      "en": "https://images.pokemontcg.io/ex9/65.png"
    }
  },
  "language": "en",
  "name": {
    "en": "Spoink"
  },
  "number": "65",
  "rarity": "c",
  "resistance": [],
  "retreat": 1,
  "set": "EM",
  "stage": "basic",
  "type": [
    "psychic"
  ],
  "weakness": [
    "psychic"
  ]
}