{
  "cardType": "trainer",
  "effect": {
    "en": "Search your discard pile for 2 different Trainer, Supporter, or Stadium cards, show them to your opponent, and your opponent chooses 1 of them. Put that card into your hand, and discard the other card. (If all Trainer, Supporter, and Stadium cards in your discard pile have the same name, choose 1 of them. Show that card to your opponent and put it into your hand.)"
  },
  "imageUrls": {
    "lg": {
      "en": "https://images.pokemontcg.io/dp7/87_hires.png"
    },
    "sm": {
      "en": "https://images.pokemontcg.io/dp7/87.png"
    },
    "xs": {
      "en": "https://images.pokemontcg.io/dp7/87.png"
    }
  },
  "language": "en",
  "name": {
    "en": "Marley's Request"
  },
  "number": "87",
  "rarity": "u",
  "set": "SF",
  "type": "supporter"
}