{
  "attacks": [
    {
      "cost": "cc",
      "dmg": "30",
      "effect": {},
      "name": {
        "jp": "かみつく"
      }
    },
    {
      "cost": "wcc",
      "dmg": "50",
      "effect": {},
      "name": {
        "jp": "みずでっぽう"
      }
    }
  ],
  "cardType": "pokemon",
  "hp": 80,
  "imageUrls": {
    "lg": {
      "jp": "https://limitlesstcg.nyc3.cdn.digitaloceanspaces.com/tpc/SD/SD_25_R_JP.png"
    },
    "sm": {
      "jp": "https://limitlesstcg.nyc3.cdn.digitaloceanspaces.com/tpc/SD/SD_25_R_JP_SM.png"
    },
    "xs": {
      "jp": "https://limitlesstcg.nyc3.cdn.digitaloceanspaces.com/tpc/SD/SD_25_R_JP_XS.png"
    }
  },
  "language": "jp",
  "name": {
    "jp": "カムカメ"
  },
  "number": "25",
  "regulation": "d",
  "resistance": [],
  "retreat": 2,
  "set": "SD",
  "stage": "basic",
  "type": [
    "water"
  ],
  "weakness": [
    "lightning"
  ]
}