{
  "attacks": [
    {
      "cost": [
        "c"
      ],
      "dmg": "30",
      "effect": {
        "en": "You may attach a [D] Energy card from your hand to 1 of your Benched Pokémon.",
        "fr": "Vous pouvez attacher une carte Énergie [D] de votre main à l'un de vos Pokémon de Banc.",
        "de": "Du kannst 1 [D]-Energiekarte aus deiner Hand an 1 Pokémon auf deiner Bank anlegen.",
        "it": "Puoi assegnare a uno dei tuoi Pokémon in panchina una carta Energia [D] dalla tua mano.",
        "pt": "Você pode ligar 1 carta de Energia [D] da sua mão a 1 dos seus Pokémon no Banco.",
        "es": "Puedes unir 1 carta de Energía [D] de tu mano a 1 de tus Pokémon en Banca."
      },
      "name": {
        "en": "Power Accelerator",
        "fr": "Accélérateur de Puissance",
        "de": "Kraftbeschleuniger",
        "it": "Accelerapotenza",
        "pt": "Aceleração Poderosa",
        "es": "Acelerador de Potencia"
      }
    },
    {
      "cost": [
        "d",
        "c",
        "c",
        "c"
      ],
      "dmg": "120+",
      "effect": {
        "en": "If your opponent's Active Pokémon is a Pokémon VMAX, this attack does 120 more damage.",
        "fr": "Si le Pokémon Actif de votre adversaire est un Pokémon-VMAX, cette attaque inflige 120 dégâts supplémentaires.",
        "de": "Wenn das Aktive Pokémon deines Gegners ein Pokémon-VMAX ist, fügt diese Attacke 120 Schadenspunkte mehr zu.",
        "it": "Se il Pokémon attivo del tuo avversario è un Pokémon-VMAX, questo attacco infligge 120 danni in più.",
        "pt": "Se o Pokémon Ativo do seu oponente for um Pokémon VMAX, este ataque causará 120 pontos de dano a mais.",
        "es": "Si el Pokémon Activo de tu rival es un Pokémon VMAX, este ataque hace 120 puntos de daño más."
      },
      "name": {
        "en": "Dynamax Cannon",
        "fr": "Canon Dynamax",
        "de": "Dynamax-Kanone",
        "it": "Cannone Dynamax",
        "pt": "Canhão Dinamax",
        "es": "Cañón Dinamax"
      }
    }
  ],
  "cardType": "pokemon",
  "hp": 220,
  "imageUrls": {
    "lg": {
      "en": "https://limitlesstcg.nyc3.cdn.digitaloceanspaces.com/tpci/SP/SP_044_R_EN.png",
      "fr": "https://limitlesstcg.nyc3.cdn.digitaloceanspaces.com/tpci/SP/SP_044_R_FR.png",
      "de": "https://limitlesstcg.nyc3.cdn.digitaloceanspaces.com/tpci/SP/SP_044_R_DE.png",
      "it": "https://limitlesstcg.nyc3.cdn.digitaloceanspaces.com/tpci/SP/SP_044_R_IT.png",
      "pt": "https://limitlesstcg.nyc3.cdn.digitaloceanspaces.com/tpci/SP/SP_044_R_PT.png",
      "es": "https://limitlesstcg.nyc3.cdn.digitaloceanspaces.com/tpci/SP/SP_044_R_ES.png"
    },
    "sm": {
      "en": "https://limitlesstcg.nyc3.cdn.digitaloceanspaces.com/tpci/SP/SP_044_R_EN_SM.png",
      "fr": "https://limitlesstcg.nyc3.cdn.digitaloceanspaces.com/tpci/SP/SP_044_R_FR_SM.png",
      "de": "https://limitlesstcg.nyc3.cdn.digitaloceanspaces.com/tpci/SP/SP_044_R_DE_SM.png",
      "it": "https://limitlesstcg.nyc3.cdn.digitaloceanspaces.com/tpci/SP/SP_044_R_IT_SM.png",
      "pt": "https://limitlesstcg.nyc3.cdn.digitaloceanspaces.com/tpci/SP/SP_044_R_PT_SM.png",
      "es": "https://limitlesstcg.nyc3.cdn.digitaloceanspaces.com/tpci/SP/SP_044_R_ES_SM.png"
    },
    "xs": {
      "en": "https://limitlesstcg.nyc3.cdn.digitaloceanspaces.com/tpci/SP/SP_044_R_EN_XS.png",
      "fr": "https://limitlesstcg.nyc3.cdn.digitaloceanspaces.com/tpci/SP/SP_044_R_FR_XS.png",
      "de": "https://limitlesstcg.nyc3.cdn.digitaloceanspaces.com/tpci/SP/SP_044_R_DE_XS.png",
      "it": "https://limitlesstcg.nyc3.cdn.digitaloceanspaces.com/tpci/SP/SP_044_R_IT_XS.png",
      "pt": "https://limitlesstcg.nyc3.cdn.digitaloceanspaces.com/tpci/SP/SP_044_R_PT_XS.png",
      "es": "https://limitlesstcg.nyc3.cdn.digitaloceanspaces.com/tpci/SP/SP_044_R_ES_XS.png"
    }
  },
  "languages": [
    "en",
    "fr",
    "de",
    "it",
    "pt",
    "es"
  ],
  "name": {
    "en": "Eternatus V",
    "fr": "Éthernatos V",
    "de": "Endynalos V",
    "it": "Eternatus V",
    "pt": "Eternatus V",
    "es": "Eternatus V"
  },
  "number": "44",
  "regulation": "d",
  "resistance": [],
  "retreat": 2,
  "set": "SP",
  "stage": "basic",
  "type": [
    "darkness"
  ],
  "weakness": [
    "fighting"
  ]
}