{
  "attacks": [
    {
      "cost": "ppc",
      "dmg": "30+",
      "effect": {
        "en": "Does 30 damage plus 20 more damage for each Energy attached to the Defending Pokémon."
      },
      "name": {
        "en": "Psywave"
      }
    }
  ],
  "cardType": "pokemon",
  "hp": 90,
  "imageUrls": {
    "lg": {
      "en": "https://images.pokemontcg.io/dp1/10_hires.png"
    },
    "sm": {
      "en": "https://images.pokemontcg.io/dp1/10.png"
    },
    "xs": {
      "en": "https://images.pokemontcg.io/dp1/10.png"
    }
  },
  "language": "en",
  "name": {
    "en": "Mismagius"
  },
  "number": "10",
  "rarity": "hr",
  "resistance": [
    "colorless"
  ],
  "retreat": 1,
  "set": "DP",
  "stage": "stage1",
  "type": [
    "psychic"
  ],
  "weakness": [
    "darkness"
  ]
}