{
  "attacks": [
    {
      "cost": [
        "c"
      ],
      "effect": {
        "en": "The Defending Pokémon is now Asleep."
      },
      "name": {
        "en": "Hypnosis"
      }
    },
    {
      "cost": [
        "c",
        "c"
      ],
      "dmg": "30",
      "effect": {
        "en": "Flip a coin. If tails, this attack does nothing."
      },
      "name": {
        "en": "Kick Shot"
      }
    }
  ],
  "cardType": "pokemon",
  "hp": 50,
  "imageUrls": {
    "lg": {
      "en": "https://images.pokemontcg.io/dp1/85_hires.png"
    },
    "sm": {
      "en": "https://images.pokemontcg.io/dp1/85.png"
    },
    "xs": {
      "en": "https://images.pokemontcg.io/dp1/85.png"
    }
  },
  "languages": [
    "en"
  ],
  "name": {
    "en": "Hoothoot"
  },
  "number": "85",
  "rarity": "c",
  "resistance": [
    "fighting"
  ],
  "retreat": 1,
  "set": "DP",
  "stage": "basic",
  "type": [
    "colorless"
  ],
  "weakness": [
    "lightning"
  ]
}