{
  "cardType": "trainer",
  "effect": {
    "en": "Heal 60 damage from your Active [N] Pokémon.",
    "fr": "Soignez 60 dégâts de votre Pokémon [N] Actif.",
    "de": "Heile 60 Schadenspunkte bei deinem Aktiven [N]-Pokémon.",
    "it": "Cura il tuo Pokémon attivo [N] da 60 danni.",
    "pt": "Cure 60 pontos de dano do seu Pokémon [N] Ativo.",
    "es": "Cura 60 puntos de daño a tu Pokémon [N] Activo."
  },
  "imageUrls": {
    "lg": {
      "en": "https://limitlesstcg.nyc3.cdn.digitaloceanspaces.com/tpci/SSP/SSP_172_R_EN.png",
      "fr": "https://limitlesstcg.nyc3.cdn.digitaloceanspaces.com/tpci/SSP/SSP_172_R_FR.png",
      "de": "https://limitlesstcg.nyc3.cdn.digitaloceanspaces.com/tpci/SSP/SSP_172_R_DE.png",
      "it": "https://limitlesstcg.nyc3.cdn.digitaloceanspaces.com/tpci/SSP/SSP_172_R_IT.png",
      "pt": "https://limitlesstcg.nyc3.cdn.digitaloceanspaces.com/tpci/SSP/SSP_172_R_PT.png",
      "es": "https://limitlesstcg.nyc3.cdn.digitaloceanspaces.com/tpci/SSP/SSP_172_R_ES.png"
    },
    "sm": {
      "en": "https://limitlesstcg.nyc3.cdn.digitaloceanspaces.com/tpci/SSP/SSP_172_R_EN_SM.png",
      "fr": "https://limitlesstcg.nyc3.cdn.digitaloceanspaces.com/tpci/SSP/SSP_172_R_FR_SM.png",
      "de": "https://limitlesstcg.nyc3.cdn.digitaloceanspaces.com/tpci/SSP/SSP_172_R_DE_SM.png",
      "it": "https://limitlesstcg.nyc3.cdn.digitaloceanspaces.com/tpci/SSP/SSP_172_R_IT_SM.png",
      "pt": "https://limitlesstcg.nyc3.cdn.digitaloceanspaces.com/tpci/SSP/SSP_172_R_PT_SM.png",
      "es": "https://limitlesstcg.nyc3.cdn.digitaloceanspaces.com/tpci/SSP/SSP_172_R_ES_SM.png"
    },
    "xs": {
      "en": "https://limitlesstcg.nyc3.cdn.digitaloceanspaces.com/tpci/SSP/SSP_172_R_EN_XS.png",
      "fr": "https://limitlesstcg.nyc3.cdn.digitaloceanspaces.com/tpci/SSP/SSP_172_R_FR_XS.png",
      "de": "https://limitlesstcg.nyc3.cdn.digitaloceanspaces.com/tpci/SSP/SSP_172_R_DE_XS.png",
      "it": "https://limitlesstcg.nyc3.cdn.digitaloceanspaces.com/tpci/SSP/SSP_172_R_IT_XS.png",
      "pt": "https://limitlesstcg.nyc3.cdn.digitaloceanspaces.com/tpci/SSP/SSP_172_R_PT_XS.png",
      "es": "https://limitlesstcg.nyc3.cdn.digitaloceanspaces.com/tpci/SSP/SSP_172_R_ES_XS.png"
    }
  },
  "languages": [
    "en",
    "fr",
    "de",
    "it",
    "pt",
    "es"
  ],
  "name": {
    "en": "Dragon Elixir",
    "fr": "Élixir de Dragon",
    "de": "Drachenelixier",
    "it": "Elisir del Drago",
    "pt": "Elixir do Dragão",
    "es": "Elixir Dragón"
  },
  "number": "172",
  "rarity": "u",
  "regulation": "h",
  "set": "SSP",
  "type": "item"
}