{
  "attacks": [
    {
      "cost": [],
      "effect": {
        "en": "Flip 3 coins. Remove a number of damage counters equal to the number of heads from your Pokémon in any way you like."
      },
      "name": {
        "en": "Magic Heal"
      }
    },
    {
      "cost": [
        "p",
        "c"
      ],
      "dmg": "30",
      "effect": {
        "en": "During your opponent's next turn, any damage done to Mr. Mime E4 by attacks is reduced by 10 (after applying Weakness and Resistance)."
      },
      "name": {
        "en": "Barrier Attack"
      }
    }
  ],
  "cardType": "pokemon",
  "hp": 70,
  "imageUrls": {
    "lg": {
      "en": "https://images.pokemontcg.io/pl2/28_hires.png"
    },
    "sm": {
      "en": "https://images.pokemontcg.io/pl2/28.png"
    },
    "xs": {
      "en": "https://images.pokemontcg.io/pl2/28.png"
    }
  },
  "languages": [
    "en"
  ],
  "name": {
    "en": "Mr. Mime E4"
  },
  "number": "28",
  "rarity": "r",
  "resistance": [],
  "retreat": 1,
  "set": "RR",
  "stage": "basic",
  "type": [
    "psychic"
  ],
  "weakness": [
    "psychic"
  ]
}