{
  "attacks": [],
  "cardType": "pokemon",
  "hp": 90,
  "imageUrls": {
    "lg": {
      "en": "https://images.pokemontcg.io/neo2/16_hires.png"
    },
    "sm": {
      "en": "https://images.pokemontcg.io/neo2/16.png"
    },
    "xs": {
      "en": "https://images.pokemontcg.io/neo2/16.png"
    }
  },
  "language": "en",
  "name": {
    "en": "Wobbuffet"
  },
  "number": "16",
  "rarity": "hr",
  "resistance": [],
  "retreat": 3,
  "set": "N2",
  "stage": "basic",
  "type": [
    "psychic"
  ],
  "weakness": [
    "psychic"
  ]
}