{
  "cardType": "trainer",
  "effect": {
    "jp": "このカードは、自分の手札を1枚トラッシュしなければ使えない。\n\n自分の手札が6枚になるように、山札を引く。"
  },
  "imageUrls": {
    "lg": {
      "jp": "https://limitlesstcg.nyc3.cdn.digitaloceanspaces.com/tpc/SV9/SV9_121_R_JP.png"
    },
    "sm": {
      "jp": "https://limitlesstcg.nyc3.cdn.digitaloceanspaces.com/tpc/SV9/SV9_121_R_JP_SM.png"
    },
    "xs": {
      "jp": "https://limitlesstcg.nyc3.cdn.digitaloceanspaces.com/tpc/SV9/SV9_121_R_JP_XS.png"
    }
  },
  "languages": [
    "jp"
  ],
  "name": {
    "jp": "アイリスの闘志"
  },
  "number": "121",
  "rarity": "sr",
  "regulation": "i",
  "set": "SV9",
  "type": "supporter"
}