{
  "attacks": [
    {
      "cost": "p",
      "dmg": "20",
      "effect": {},
      "name": {
        "jp": "ねんどうだん"
      }
    }
  ],
  "cardType": "pokemon",
  "hp": 110,
  "imageUrls": {
    "lg": {
      "jp": "https://limitlesstcg.nyc3.cdn.digitaloceanspaces.com/tpc/SV9/SV9_40_R_JP.png"
    },
    "sm": {
      "jp": "https://limitlesstcg.nyc3.cdn.digitaloceanspaces.com/tpc/SV9/SV9_40_R_JP_SM.png"
    },
    "xs": {
      "jp": "https://limitlesstcg.nyc3.cdn.digitaloceanspaces.com/tpc/SV9/SV9_40_R_JP_XS.png"
    }
  },
  "language": "jp",
  "name": {
    "jp": "Nのシンボラー"
  },
  "number": "40",
  "rarity": "c",
  "regulation": "i",
  "resistance": [
    "fighting"
  ],
  "retreat": 1,
  "set": "SV9",
  "stage": "basic",
  "type": [
    "psychic"
  ],
  "weakness": [
    "lightning"
  ]
}