{
  "attacks": [],
  "cardType": "pokemon",
  "hp": 50,
  "imageUrls": {
    "lg": {
      "en": "https://images.pokemontcg.io/ex1/74_hires.png"
    },
    "sm": {
      "en": "https://images.pokemontcg.io/ex1/74.png"
    },
    "xs": {
      "en": "https://images.pokemontcg.io/ex1/74.png"
    }
  },
  "language": "en",
  "name": {
    "en": "Torchic"
  },
  "number": "74",
  "rarity": "c",
  "resistance": [],
  "retreat": 1,
  "set": "RS",
  "stage": "basic",
  "type": [
    "fire"
  ],
  "weakness": [
    "water"
  ]
}