{
  "attacks": [
    {
      "cost": [
        "c"
      ],
      "effect": {
        "en": "Shuffle your opponent's deck."
      },
      "name": {
        "en": "Mischief"
      }
    },
    {
      "cost": [
        "f",
        "c"
      ],
      "dmg": "30",
      "effect": {},
      "name": {
        "en": "Light Punch"
      }
    }
  ],
  "cardType": "pokemon",
  "hp": 50,
  "imageUrls": {
    "lg": {
      "en": "https://images.pokemontcg.io/ex6/38_hires.png"
    },
    "sm": {
      "en": "https://images.pokemontcg.io/ex6/38.png"
    },
    "xs": {
      "en": "https://images.pokemontcg.io/ex6/38.png"
    }
  },
  "languages": [
    "en"
  ],
  "name": {
    "en": "Mankey"
  },
  "number": "38",
  "rarity": "u",
  "resistance": [],
  "retreat": 1,
  "set": "RG",
  "stage": "basic",
  "type": [
    "fighting"
  ],
  "weakness": [
    "psychic"
  ]
}