{
  "attacks": [
    {
      "cost": [
        "c"
      ],
      "effect": {
        "en": "Each player draws and reveals the top card of his or her deck.",
        "fr": "Chaque joueur pioche et dévoile la carte du dessus de son deck.",
        "de": "Jeder Spieler zieht die oberste Karte seines Decks, zeigt sie seinem Gegner und nimmt sie auf die Hand.",
        "it": "Ogni giocatore pesca e scopre la carta in cima al proprio mazzo."
      },
      "name": {
        "en": "Rendezvous Draw",
        "fr": "Pioche commune",
        "de": "Verabredungszieher",
        "it": "Pescappuntamento"
      }
    },
    {
      "cost": [
        "w"
      ],
      "dmg": "30",
      "effect": {
        "en": "Before doing damage, remove 1 damage counter from the Defending Pokémon.",
        "fr": "Avant d'infliger des dégâts, retirez un marqueur de dégât au Pokémon Défenseur.",
        "de": "Bevor der Schaden zugefügt wird, entferne 1 Schadensmarke vom Verteidigenden Pokémon.",
        "it": "Prima di infliggere danno, togli 1 segnalino danno dal Pokémon Difensore."
      },
      "name": {
        "en": "Distorted Wave",
        "fr": "Vague tordue",
        "de": "Verzerrte Welle",
        "it": "Onda Distorta"
      }
    }
  ],
  "cardType": "pokemon",
  "hp": 60,
  "imageUrls": {
    "lg": {
      "en": "https://limitlesstcg.nyc3.cdn.digitaloceanspaces.com/tpci/TM/TM_039_R_EN.png",
      "fr": "https://limitlesstcg.nyc3.cdn.digitaloceanspaces.com/tpci/TM/TM_039_R_FR.png",
      "de": "https://limitlesstcg.nyc3.cdn.digitaloceanspaces.com/tpci/TM/TM_039_R_DE.png",
      "it": "https://limitlesstcg.nyc3.cdn.digitaloceanspaces.com/tpci/TM/TM_039_R_IT.png",
      "pt": "https://limitlesstcg.nyc3.cdn.digitaloceanspaces.com/tpci/TM/TM_039_R_PT.png",
      "es": "https://limitlesstcg.nyc3.cdn.digitaloceanspaces.com/tpci/TM/TM_039_R_ES.png"
    },
    "sm": {
      "en": "https://limitlesstcg.nyc3.cdn.digitaloceanspaces.com/tpci/TM/TM_039_R_EN_SM.png",
      "fr": "https://limitlesstcg.nyc3.cdn.digitaloceanspaces.com/tpci/TM/TM_039_R_FR_SM.png",
      "de": "https://limitlesstcg.nyc3.cdn.digitaloceanspaces.com/tpci/TM/TM_039_R_DE_SM.png",
      "it": "https://limitlesstcg.nyc3.cdn.digitaloceanspaces.com/tpci/TM/TM_039_R_IT_SM.png",
      "pt": "https://limitlesstcg.nyc3.cdn.digitaloceanspaces.com/tpci/TM/TM_039_R_PT_SM.png",
      "es": "https://limitlesstcg.nyc3.cdn.digitaloceanspaces.com/tpci/TM/TM_039_R_ES_SM.png"
    },
    "xs": {
      "en": "https://limitlesstcg.nyc3.cdn.digitaloceanspaces.com/tpci/TM/TM_039_R_EN_XS.png",
      "fr": "https://limitlesstcg.nyc3.cdn.digitaloceanspaces.com/tpci/TM/TM_039_R_FR_XS.png",
      "de": "https://limitlesstcg.nyc3.cdn.digitaloceanspaces.com/tpci/TM/TM_039_R_DE_XS.png",
      "it": "https://limitlesstcg.nyc3.cdn.digitaloceanspaces.com/tpci/TM/TM_039_R_IT_XS.png",
      "pt": "https://limitlesstcg.nyc3.cdn.digitaloceanspaces.com/tpci/TM/TM_039_R_PT_XS.png",
      "es": "https://limitlesstcg.nyc3.cdn.digitaloceanspaces.com/tpci/TM/TM_039_R_ES_XS.png"
    }
  },
  "language": "en",
  "name": {
    "en": "Luvdisc",
    "fr": "Lovdisc",
    "de": "Liebiskus",
    "it": "Luvdisc",
    "pt": "Luvdisc",
    "es": "Luvdisc"
  },
  "number": "39",
  "rarity": "u",
  "resistance": [],
  "retreat": 1,
  "set": "TM",
  "stage": "basic",
  "type": [
    "water"
  ],
  "weakness": [
    "lightning"
  ]
}