{
  "cardType": "trainer",
  "effect": {
    "en": "The Retreat Cost of the Pokémon this card is attached to is [C][C] less.",
    "fr": "Le Coût de Retraite du Pokémon auquel cette carte est attachée est diminué de [C][C].",
    "de": "Die Rückzugskosten des Pokémon, an das diese Karte angelegt ist, verringern sich um [C][C].",
    "it": "Il costo di ritirata del Pokémon a cui è assegnata questa carta è ridotto di [C][C].",
    "pt": "O custo de Recuo do Pokémon ao qual esta carta está ligada é [C][C] a menos.",
    "es": "El Coste de Retirada del Pokémon al que está unida esta carta es de [C][C] menos."
  },
  "imageUrls": {
    "lg": {
      "en": "https://limitlesstcg.nyc3.cdn.digitaloceanspaces.com/tpci/SSH/SSH_156_R_EN.png",
      "fr": "https://limitlesstcg.nyc3.cdn.digitaloceanspaces.com/tpci/SSH/SSH_156_R_FR.png",
      "de": "https://limitlesstcg.nyc3.cdn.digitaloceanspaces.com/tpci/SSH/SSH_156_R_DE.png",
      "it": "https://limitlesstcg.nyc3.cdn.digitaloceanspaces.com/tpci/SSH/SSH_156_R_IT.png",
      "pt": "https://limitlesstcg.nyc3.cdn.digitaloceanspaces.com/tpci/SSH/SSH_156_R_PT.png",
      "es": "https://limitlesstcg.nyc3.cdn.digitaloceanspaces.com/tpci/SSH/SSH_156_R_ES.png"
    },
    "sm": {
      "en": "https://limitlesstcg.nyc3.cdn.digitaloceanspaces.com/tpci/SSH/SSH_156_R_EN_SM.png",
      "fr": "https://limitlesstcg.nyc3.cdn.digitaloceanspaces.com/tpci/SSH/SSH_156_R_FR_SM.png",
      "de": "https://limitlesstcg.nyc3.cdn.digitaloceanspaces.com/tpci/SSH/SSH_156_R_DE_SM.png",
      "it": "https://limitlesstcg.nyc3.cdn.digitaloceanspaces.com/tpci/SSH/SSH_156_R_IT_SM.png",
      "pt": "https://limitlesstcg.nyc3.cdn.digitaloceanspaces.com/tpci/SSH/SSH_156_R_PT_SM.png",
      "es": "https://limitlesstcg.nyc3.cdn.digitaloceanspaces.com/tpci/SSH/SSH_156_R_ES_SM.png"
    },
    "xs": {
      "en": "https://limitlesstcg.nyc3.cdn.digitaloceanspaces.com/tpci/SSH/SSH_156_R_EN_XS.png",
      "fr": "https://limitlesstcg.nyc3.cdn.digitaloceanspaces.com/tpci/SSH/SSH_156_R_FR_XS.png",
      "de": "https://limitlesstcg.nyc3.cdn.digitaloceanspaces.com/tpci/SSH/SSH_156_R_DE_XS.png",
      "it": "https://limitlesstcg.nyc3.cdn.digitaloceanspaces.com/tpci/SSH/SSH_156_R_IT_XS.png",
      "pt": "https://limitlesstcg.nyc3.cdn.digitaloceanspaces.com/tpci/SSH/SSH_156_R_PT_XS.png",
      "es": "https://limitlesstcg.nyc3.cdn.digitaloceanspaces.com/tpci/SSH/SSH_156_R_ES_XS.png"
    }
  },
  "language": "en",
  "name": {
    "en": "Air Balloon",
    "fr": "Ballon",
    "de": "Luftballon",
    "it": "Palloncino",
    "pt": "Balão de Ar",
    "es": "Globo Helio"
  },
  "number": "156",
  "rarity": "u",
  "regulation": "d",
  "set": "SSH",
  "type": "tool"
}