{
  "attacks": [
    {
      "cost": "wwww",
      "dmg": "70",
      "effect": {
        "en": "You may put 2 Energy attached to your opponent's Active Pokémon into their hand.",
        "fr": "Vous pouvez ajouter à la main de votre adversaire jusqu'à 2 Énergies attachées à son Pokémon Actif.",
        "de": "Du kannst deinem Gegner 2 an sein Aktives Pokémon angelegte Energien auf seine Hand geben.",
        "it": "Puoi prendere due Energie assegnate al Pokémon attivo del tuo avversario e aggiungerle alle carte che ha in mano.",
        "pt": "Você pode colocar 2 Energias ligadas ao Pokémon Ativo do seu oponente na mão dele(a).",
        "es": "Puedes poner 2 Energías unidas al Pokémon Activo de tu rival en su mano."
      },
      "name": {
        "en": "Aqua Wash",
        "fr": "Aqua-Lavage",
        "de": "Aquawäsche",
        "it": "Idrolavaggio",
        "pt": "Limpeza Aquática",
        "es": "Limpieza Acuática"
      }
    }
  ],
  "cardType": "pokemon",
  "hp": 130,
  "imageUrls": {
    "lg": {
      "en": "https://limitlesstcg.nyc3.cdn.digitaloceanspaces.com/tpci/SSH/SSH_048_R_EN.png",
      "fr": "https://limitlesstcg.nyc3.cdn.digitaloceanspaces.com/tpci/SSH/SSH_048_R_FR.png",
      "de": "https://limitlesstcg.nyc3.cdn.digitaloceanspaces.com/tpci/SSH/SSH_048_R_DE.png",
      "it": "https://limitlesstcg.nyc3.cdn.digitaloceanspaces.com/tpci/SSH/SSH_048_R_IT.png",
      "pt": "https://limitlesstcg.nyc3.cdn.digitaloceanspaces.com/tpci/SSH/SSH_048_R_PT.png",
      "es": "https://limitlesstcg.nyc3.cdn.digitaloceanspaces.com/tpci/SSH/SSH_048_R_ES.png"
    },
    "sm": {
      "en": "https://limitlesstcg.nyc3.cdn.digitaloceanspaces.com/tpci/SSH/SSH_048_R_EN_SM.png",
      "fr": "https://limitlesstcg.nyc3.cdn.digitaloceanspaces.com/tpci/SSH/SSH_048_R_FR_SM.png",
      "de": "https://limitlesstcg.nyc3.cdn.digitaloceanspaces.com/tpci/SSH/SSH_048_R_DE_SM.png",
      "it": "https://limitlesstcg.nyc3.cdn.digitaloceanspaces.com/tpci/SSH/SSH_048_R_IT_SM.png",
      "pt": "https://limitlesstcg.nyc3.cdn.digitaloceanspaces.com/tpci/SSH/SSH_048_R_PT_SM.png",
      "es": "https://limitlesstcg.nyc3.cdn.digitaloceanspaces.com/tpci/SSH/SSH_048_R_ES_SM.png"
    },
    "xs": {
      "en": "https://limitlesstcg.nyc3.cdn.digitaloceanspaces.com/tpci/SSH/SSH_048_R_EN_XS.png",
      "fr": "https://limitlesstcg.nyc3.cdn.digitaloceanspaces.com/tpci/SSH/SSH_048_R_FR_XS.png",
      "de": "https://limitlesstcg.nyc3.cdn.digitaloceanspaces.com/tpci/SSH/SSH_048_R_DE_XS.png",
      "it": "https://limitlesstcg.nyc3.cdn.digitaloceanspaces.com/tpci/SSH/SSH_048_R_IT_XS.png",
      "pt": "https://limitlesstcg.nyc3.cdn.digitaloceanspaces.com/tpci/SSH/SSH_048_R_PT_XS.png",
      "es": "https://limitlesstcg.nyc3.cdn.digitaloceanspaces.com/tpci/SSH/SSH_048_R_ES_XS.png"
    }
  },
  "language": "en",
  "name": {
    "en": "Lapras",
    "fr": "Lokhlass",
    "de": "Lapras",
    "it": "Lapras",
    "pt": "Lapras",
    "es": "Lapras"
  },
  "number": "48",
  "rarity": "r",
  "regulation": "d",
  "resistance": [],
  "retreat": 3,
  "set": "SSH",
  "stage": "basic",
  "type": [
    "water"
  ],
  "weakness": [
    "lightning"
  ]
}