{
  "attacks": [
    {
      "cost": [
        "c"
      ],
      "effect": {
        "en": "The Defending Pokémon is now Asleep."
      },
      "name": {
        "en": "Lullaby"
      }
    },
    {
      "cost": [
        "c",
        "c",
        "c"
      ],
      "dmg": "10+",
      "effect": {
        "en": "Does 10 damage plus 10 more damage for each of your Benched Pokémon."
      },
      "name": {
        "en": "Do the Wave"
      }
    }
  ],
  "cardType": "pokemon",
  "hp": 80,
  "imageUrls": {
    "lg": {
      "en": "https://images.pokemontcg.io/base2/32_hires.png"
    },
    "sm": {
      "en": "https://images.pokemontcg.io/base2/32.png"
    },
    "xs": {
      "en": "https://images.pokemontcg.io/base2/32.png"
    }
  },
  "language": "en",
  "name": {
    "en": "Wigglytuff"
  },
  "number": "32",
  "rarity": "r",
  "resistance": [
    "psychic"
  ],
  "retreat": 2,
  "set": "JU",
  "stage": "stage1",
  "type": [
    "colorless"
  ],
  "weakness": [
    "fighting"
  ]
}