{
  "attacks": [
    {
      "cost": [
        "c"
      ],
      "effect": {
        "jp": "コインを1回投げオモテなら、相手のバトルポケモンをマヒにする。"
      },
      "name": {
        "jp": "へびにらみ"
      }
    },
    {
      "cost": [
        "c",
        "c"
      ],
      "dmg": "10+",
      "effect": {
        "jp": "相手のバトルポケモンにのっているダメカンの数x10ダメージを追加。"
      },
      "name": {
        "jp": "きずにかみつく"
      }
    }
  ],
  "cardType": "pokemon",
  "hp": 40,
  "imageUrls": {
    "lg": {
      "jp": "https://limitlesstcg.nyc3.cdn.digitaloceanspaces.com/tpc/XY1x/XY1x_46_R_JP.png"
    },
    "sm": {
      "jp": "https://limitlesstcg.nyc3.cdn.digitaloceanspaces.com/tpc/XY1x/XY1x_46_R_JP_SM.png"
    },
    "xs": {
      "jp": "https://limitlesstcg.nyc3.cdn.digitaloceanspaces.com/tpc/XY1x/XY1x_46_R_JP_XS.png"
    }
  },
  "language": "jp",
  "name": {
    "jp": "ノコッチ"
  },
  "number": "46",
  "rarity": "c",
  "resistance": [],
  "retreat": 0,
  "set": "XY1x",
  "stage": "basic",
  "type": [
    "colorless"
  ],
  "weakness": [
    "fighting"
  ]
}