{
  "attacks": [
    {
      "cost": [
        "c",
        "c"
      ],
      "dmg": "10",
      "effect": {
        "en": "If your opponent has any Benched Pokémon, he or she chooses 1 of them and switches it with the Defending Pokémon. (Do the damage before switching the Pokémon.)"
      },
      "name": {
        "en": "Whirlwind"
      }
    }
  ],
  "cardType": "pokemon",
  "hp": 40,
  "imageUrls": {
    "lg": {
      "en": "https://images.pokemontcg.io/base4/86_hires.png"
    },
    "sm": {
      "en": "https://images.pokemontcg.io/base4/86.png"
    },
    "xs": {
      "en": "https://images.pokemontcg.io/base4/86.png"
    }
  },
  "language": "en",
  "name": {
    "en": "Pidgey"
  },
  "number": "86",
  "rarity": "c",
  "resistance": [
    "fighting"
  ],
  "retreat": 1,
  "set": "BS2",
  "stage": "basic",
  "type": [
    "colorless"
  ],
  "weakness": [
    "lightning"
  ]
}